mcpd/__init__.py
mcpd/_logger.py
mcpd/dynamic_caller.py
mcpd/exceptions.py
mcpd/function_builder.py
mcpd/mcpd_client.py
mcpd/py.typed
mcpd/type_converter.py
mcpd-0.1.0.dist-info/licenses/LICENSE
mcpd-0.1.0.dist-info/METADATA
mcpd-0.1.0.dist-info/WHEEL
mcpd-0.1.0.dist-info/top_level.txt
mcpd-0.1.0.dist-info/RECORD
