Metadata-Version: 2.4
Name: mcpd
Version: 0.1.0
Summary: mcpd Python SDK
License: Apache-2.0
Requires-Python: >=3.11
License-File: LICENSE
Requires-Dist: cachetools>=6.2.0
Requires-Dist: requests>=2.32.4
Dynamic: license-file
